aws_ssh_utils/__init__.py
aws_ssh_utils/emr_utils.py
aws_ssh_utils/interactive_ssh.py
aws_ssh_utils/py.typed
aws_ssh_utils/ssh.py
aws_ssh_utils-0.2.4.dist-info/METADATA
aws_ssh_utils-0.2.4.dist-info/WHEEL
aws_ssh_utils-0.2.4.dist-info/entry_points.txt
aws_ssh_utils-0.2.4.dist-info/licenses/LICENSE
aws_ssh_utils-0.2.4.dist-info/RECORD
