Metadata-Version: 2.4
Name: aws-ssh-utils
Version: 0.2.4
Summary: Easy AWS SSHing
Project-URL: Homepage, https://github.com/mvanderlee/aws-ssh-utils
Author-email: Michiel Vanderlee <jmt.vanderlee@gmail.com>
License-Expression: MIT
License-File: LICENSE
Classifier: Intended Audience :: Developers
Classifier: Intended Audience :: Information Technology
Classifier: Intended Audience :: System Administrators
Classifier: License :: OSI Approved :: MIT License
Classifier: Operating System :: OS Independent
Classifier: Programming Language :: Python
Classifier: Programming Language :: Python :: 3 :: Only
Classifier: Programming Language :: Python :: 3.11
Classifier: Programming Language :: Python :: 3.12
Classifier: Programming Language :: Python :: 3.13
Classifier: Topic :: Software Development
Classifier: Topic :: Software Development :: Libraries
Classifier: Topic :: Software Development :: Libraries :: Python Modules
Classifier: Typing :: Typed
Requires-Python: >=3.11
Requires-Dist: boto3
Requires-Dist: click
Requires-Dist: click-spinner
Requires-Dist: coloredlogs
Requires-Dist: environs
Requires-Dist: loguru
Requires-Dist: paramiko
Requires-Dist: questionary
Requires-Dist: typing-extensions
Provides-Extra: dev
Requires-Dist: boto3-stubs[ec2,emr]; extra == 'dev'
Provides-Extra: publish
Requires-Dist: hatch>=1.7.0; extra == 'publish'
Provides-Extra: test
